pythoncalc/__init__.py
pradyumncalc2-0.1.dist-info/LICENCE.txt
pradyumncalc2-0.1.dist-info/METADATA
pradyumncalc2-0.1.dist-info/WHEEL
pradyumncalc2-0.1.dist-info/top_level.txt
pradyumncalc2-0.1.dist-info/RECORD
