Metadata-Version: 2.1
Name: pradyumncalc2
Version: 0.1
Summary: A calculator that can calculate Basic operations, simple interest and compound interest
Home-page: UNKNOWN
Author: Pradyumn
Author-email: gargpradyumn4@gmail.com
License: UNKNOWN
Platform: UNKNOWN
Classifier: Programming Language :: Python :: 3
Classifier: License :: OSI Approved :: MIT License
Classifier: Operating System :: OS Independent
License-File: LICENCE.txt
